git_warden.py
setup.py
git_warden.egg-info/PKG-INFO
git_warden.egg-info/SOURCES.txt
git_warden.egg-info/dependency_links.txt
git_warden.egg-info/requires.txt
git_warden.egg-info/top_level.txt