Metadata-Version: 1.0
Name: git-warden
Version: 0.0.6
Summary: Batch Git repository manager
Home-page: http://www.github.com/Ceasar/git_warden
Author: Ceasar Bautista
Author-email: cbautista2010@gmail.com
License: UNKNOWN
Platform: UNKNOWN
